mcpack/__init__.py
mcpack/datapack.py
mcpack-0.3.9.dist-info/LICENSE
mcpack-0.3.9.dist-info/WHEEL
mcpack-0.3.9.dist-info/METADATA
mcpack-0.3.9.dist-info/RECORD
